rocketTestSoufiane/__init__.py
rocketTestSoufiane/rocket.py
rockettestsoufiane-1.0.0.dist-info/licenses/LICENSE.txt
rockettestsoufiane-1.0.0.dist-info/METADATA
rockettestsoufiane-1.0.0.dist-info/WHEEL
rockettestsoufiane-1.0.0.dist-info/top_level.txt
rockettestsoufiane-1.0.0.dist-info/RECORD
