Metadata-Version: 2.4
Name: rocketTestSoufiane
Version: 1.0.0
Summary: An awesome package that does something
Home-page: http://pypi.python.org/pypi/rocketTestSoufiane/
Author: Bensetallah soufiane
Author-email: rtsof91@gmail.com
License: LICENSE.txt
License-File: LICENSE.txt
Dynamic: author
Dynamic: author-email
Dynamic: description
Dynamic: description-content-type
Dynamic: home-page
Dynamic: license
Dynamic: license-file
Dynamic: summary
